{"version":1,"resource":"file:///home/yusof_0090/Projects/pharmacy_management/Python/src/seed/runner.py","entries":[{"id":"AwUs.py","timestamp":1772191399145},{"id":"YhuW.py","timestamp":1772192168857},{"id":"Sr4i.py","timestamp":1772192910381},{"id":"4wBb.py","timestamp":1772279700862},{"id":"0xmu.py","timestamp":1772281803422},{"id":"entw.py","timestamp":1772282464520},{"id":"1D9a.py","timestamp":1772698930042},{"id":"13qv.py","timestamp":1772791060309},{"id":"ZwGL.py","timestamp":1772791079165},{"id":"BQfo.py","timestamp":1772792283046}]}